cTTS/__init__.py
cTTS-0.0.3.dist-info/LICENSE
cTTS-0.0.3.dist-info/METADATA
cTTS-0.0.3.dist-info/WHEEL
cTTS-0.0.3.dist-info/top_level.txt
cTTS-0.0.3.dist-info/RECORD
