Metadata-Version: 2.1
Name: cTTS
Version: 0.0.3
Summary: Python module for using a Coqui TTS server
Home-page: https://github.com/thorstenMueller/cTTS
Author: Thorsten Müller
Author-email: tm@thorsten-voice.de
License: Mozilla Public License Version 2.0
Requires-Python: >=3.4
License-File: LICENSE
Requires-Dist: setuptools (>=42)
Requires-Dist: wheel
Requires-Dist: response
